unmap/__init__.py
unmap/_version.py
unmap/unmap.py
unmap/unweave.py
unmap-0.1.2.dist-info/AUTHORS.md
unmap-0.1.2.dist-info/LICENSE
unmap-0.1.2.dist-info/METADATA
unmap-0.1.2.dist-info/WHEEL
unmap-0.1.2.dist-info/top_level.txt
unmap-0.1.2.dist-info/RECORD
