Metadata-Version: 2.1
Name: unmap
Version: 0.1.2
Summary: Unmap data from pseudocolor images.
Home-page: https://github.com/kwinkunks/unmap
Author: Matt Hall
Author-email: kwinkunks@gmail.com
Classifier: Intended Audience :: Science/Research
Classifier: Development Status :: 3 - Alpha
Classifier: Natural Language :: English
Classifier: Programming Language :: Python :: 3.8
Classifier: Programming Language :: Python :: 3.9
Classifier: Programming Language :: Python :: 3.10
Classifier: License :: OSI Approved :: Apache Software License
Classifier: Operating System :: OS Independent
Requires-Python: >=3.8
License-File: LICENSE
License-File: AUTHORS.md
Requires-Dist: numpy
Requires-Dist: scipy
Requires-Dist: fsspec
Requires-Dist: aiohttp
Requires-Dist: pillow
Requires-Dist: xarray
Requires-Dist: networkx
Requires-Dist: matplotlib
Requires-Dist: scikit-image
Provides-Extra: dev
Requires-Dist: pytest ; extra == 'dev'
Requires-Dist: pytest-cov ; extra == 'dev'
Requires-Dist: sphinx ; extra == 'dev'
Requires-Dist: sphinxcontrib-apidoc ; extra == 'dev'
Requires-Dist: furo ; extra == 'dev'
Requires-Dist: myst-nb ; extra == 'dev'
Requires-Dist: gio ; extra == 'dev'
Provides-Extra: docs
Requires-Dist: sphinx ; extra == 'docs'
Requires-Dist: sphinxcontrib-apidoc ; extra == 'docs'
Requires-Dist: furo ; extra == 'docs'
Requires-Dist: myst-nb ; extra == 'docs'
Requires-Dist: gio ; extra == 'docs'
Provides-Extra: test
Requires-Dist: pytest ; extra == 'test'
Requires-Dist: pytest-cov ; extra == 'test'
